{
  "meta": {
    "updated_at": "2026-06-09 05:58:00"
  },
  "dashboard": {
    "crypto_fear_index": 10,
    "crypto_fear_label": "Extreme Fear",
    "stock_market_mood": 50,
    "market_summary_headline": "Opportunity: BTC",
    "market_summary_body": "AI Strategy Engine has completed a full market scan. Volatility detected in key sectors. Check detailed signals below."
  },
  "signals": [
    {
      "id": "BTC_1780984680",
      "symbol": "BTC",
      "asset_type": "Crypto",
      "price": "63295.97",
      "signal_type": "Watching",
      "action": "Watch",
      "value_display": "Choppy",
      "score": 50,
      "ai_analysis": "MACD momentum is weakening, potential pullback ahead.  RSI dropped to 26.6, entering [Oversold] zone. Rebound likely.",
      "sparkline": [
        64014.3671875,
        63801.57421875,
        60922.66796875,
        60867.4140625,
        63239.51953125,
        63239.51953125,
        63295.96875
      ],
      "stats": {
        "rsi": "26.6",
        "vol_ratio": "0.9x",
        "high_24h": "63484.54",
        "low_24h": "62420.56"
      }
    },
    {
      "id": "ETH_1780984680",
      "symbol": "ETH",
      "asset_type": "Crypto",
      "price": "1686.73",
      "signal_type": "Watching",
      "action": "Watch",
      "value_display": "Choppy",
      "score": 50,
      "ai_analysis": "MACD momentum is weakening, potential pullback ahead.  RSI dropped to 27.7, entering [Oversold] zone. Rebound likely.",
      "sparkline": [
        1811.7322998046875,
        1769.58056640625,
        1580.86083984375,
        1568.7677001953125,
        1686.396240234375,
        1686.396240234375,
        1686.72998046875
      ],
      "stats": {
        "rsi": "27.7",
        "vol_ratio": "1.0x",
        "high_24h": "1692.89",
        "low_24h": "1656.10"
      }
    },
    {
      "id": "SOL_1780984680",
      "symbol": "SOL",
      "asset_type": "Crypto",
      "price": "67.10",
      "signal_type": "Watching",
      "action": "Watch",
      "value_display": "Choppy",
      "score": 50,
      "ai_analysis": "MACD momentum is weakening, potential pullback ahead.  RSI dropped to 29.6, entering [Oversold] zone. Rebound likely.",
      "sparkline": [
        71.61238098144531,
        68.71892547607422,
        63.486942291259766,
        62.18980407714844,
        66.31063079833984,
        66.31063079833984,
        67.0999984741211
      ],
      "stats": {
        "rsi": "29.6",
        "vol_ratio": "0.8x",
        "high_24h": "67.23",
        "low_24h": "65.42"
      }
    },
    {
      "id": "BNB_1780984680",
      "symbol": "BNB",
      "asset_type": "Crypto",
      "price": "603.30",
      "signal_type": "Watching",
      "action": "Watch",
      "value_display": "Choppy",
      "score": 50,
      "ai_analysis": "MACD momentum is weakening, potential pullback ahead.  RSI (41.8) is in neutral zone.",
      "sparkline": [
        620.0994262695312,
        603.5347290039062,
        572.1068725585938,
        574.5108032226562,
        603.6289672851562,
        603.6289672851562,
        603.2999877929688
      ],
      "stats": {
        "rsi": "41.8",
        "vol_ratio": "0.6x",
        "high_24h": "604.43",
        "low_24h": "593.48"
      }
    },
    {
      "id": "DOGE_1780984680",
      "symbol": "DOGE",
      "asset_type": "Crypto",
      "price": "0.09",
      "signal_type": "Watching",
      "action": "Watch",
      "value_display": "Choppy",
      "score": 50,
      "ai_analysis": "MACD momentum is weakening, potential pullback ahead.  RSI (31.8) is in neutral zone.",
      "sparkline": [
        0.0913579985499382,
        0.08838000148534775,
        0.08135999739170074,
        0.0818530023097992,
        0.08608900010585785,
        0.08608900010585785,
        0.08640000224113464
      ],
      "stats": {
        "rsi": "31.8",
        "vol_ratio": "0.7x",
        "high_24h": "0.09",
        "low_24h": "0.08"
      }
    },
    {
      "id": "XRP_1780984680",
      "symbol": "XRP",
      "asset_type": "Crypto",
      "price": "1.17",
      "signal_type": "Watching",
      "action": "Watch",
      "value_display": "Choppy",
      "score": 50,
      "ai_analysis": "MACD momentum is weakening, potential pullback ahead.  RSI (35.0) is in neutral zone.",
      "sparkline": [
        1.2002509832382202,
        1.166646957397461,
        1.0964360237121582,
        1.0934580564498901,
        1.1546510457992554,
        1.1546510457992554,
        1.1717000007629395
      ],
      "stats": {
        "rsi": "35.0",
        "vol_ratio": "1.0x",
        "high_24h": "1.17",
        "low_24h": "1.14"
      }
    },
    {
      "id": "SHIB_1780984680",
      "symbol": "SHIB",
      "asset_type": "Crypto",
      "price": "0.00",
      "signal_type": "Watching",
      "action": "Watch",
      "value_display": "Choppy",
      "score": 50,
      "ai_analysis": "MACD momentum is weakening, potential pullback ahead.  RSI (31.9) is in neutral zone.  Volume is extremely low, market is waiting for direction.",
      "sparkline": [
        4.999999873689376e-06,
        4.999999873689376e-06,
        4.999999873689376e-06,
        4.999999873689376e-06,
        4.999999873689376e-06,
        4.999999873689376e-06,
        4.7399998948094435e-06
      ],
      "stats": {
        "rsi": "31.9",
        "vol_ratio": "0.6x",
        "high_24h": "0.00",
        "low_24h": "0.00"
      }
    },
    {
      "id": "WIF_1780984680",
      "symbol": "WIF",
      "asset_type": "Crypto",
      "price": "0.16",
      "signal_type": "Watching",
      "action": "Watch",
      "value_display": "Choppy",
      "score": 50,
      "ai_analysis": "MACD momentum is weakening, potential pullback ahead.  RSI (36.4) is in neutral zone.",
      "sparkline": [
        0.18966799974441528,
        0.16707399487495422,
        0.15246599912643433,
        0.15236100554466248,
        0.15836100280284882,
        0.15836100280284882,
        0.1589999943971634
      ],
      "stats": {
        "rsi": "36.4",
        "vol_ratio": "1.3x",
        "high_24h": "0.16",
        "low_24h": "0.15"
      }
    },
    {
      "id": "SPY_1780984680",
      "symbol": "SPY",
      "asset_type": "Stock",
      "price": "739.22",
      "signal_type": "Watching",
      "action": "Watch",
      "value_display": "Choppy",
      "score": 50,
      "ai_analysis": "MACD momentum is weakening, potential pullback ahead.  RSI (44.9) is in neutral zone.",
      "sparkline": [
        754.239990234375,
        757.0900268554688,
        737.5499877929688,
        737.5499877929688,
        737.5499877929688,
        739.219970703125,
        739.219970703125
      ],
      "stats": {
        "rsi": "44.9",
        "vol_ratio": "0.9x",
        "high_24h": "745.34",
        "low_24h": "738.19"
      }
    },
    {
      "id": "QQQ_1780984680",
      "symbol": "QQQ",
      "asset_type": "Stock",
      "price": "716.07",
      "signal_type": "Watching",
      "action": "Watch",
      "value_display": "Choppy",
      "score": 50,
      "ai_analysis": "MACD momentum is weakening, potential pullback ahead.  RSI (49.6) is in neutral zone.",
      "sparkline": [
        744.2100219726562,
        740.6099853515625,
        705.0599975585938,
        705.0599975585938,
        705.0599975585938,
        716.0700073242188,
        716.0700073242188
      ],
      "stats": {
        "rsi": "49.6",
        "vol_ratio": "1.0x",
        "high_24h": "723.03",
        "low_24h": "713.07"
      }
    },
    {
      "id": "NVDA_1780984680",
      "symbol": "NVDA",
      "asset_type": "Stock",
      "price": "208.64",
      "signal_type": "Watching",
      "action": "Watch",
      "value_display": "Choppy",
      "score": 50,
      "ai_analysis": "MACD momentum is weakening, potential pullback ahead.  RSI (45.4) is in neutral zone.",
      "sparkline": [
        214.5,
        218.66000366210938,
        205.10000610351562,
        205.10000610351562,
        205.10000610351562,
        208.63999938964844,
        208.63999938964844
      ],
      "stats": {
        "rsi": "45.4",
        "vol_ratio": "0.7x",
        "high_24h": "210.47",
        "low_24h": "206.00"
      }
    },
    {
      "id": "TSLA_1780984680",
      "symbol": "TSLA",
      "asset_type": "Stock",
      "price": "408.95",
      "signal_type": "Watching",
      "action": "Watch",
      "value_display": "Choppy",
      "score": 50,
      "ai_analysis": "MACD momentum is weakening, potential pullback ahead.  RSI (46.5) is in neutral zone.",
      "sparkline": [
        423.70001220703125,
        418.45001220703125,
        391.0,
        391.0,
        391.0,
        408.95001220703125,
        408.95001220703125
      ],
      "stats": {
        "rsi": "46.5",
        "vol_ratio": "1.1x",
        "high_24h": "412.94",
        "low_24h": "394.72"
      }
    },
    {
      "id": "AAPL_1780984680",
      "symbol": "AAPL",
      "asset_type": "Stock",
      "price": "301.54",
      "signal_type": "Watching",
      "action": "Watch",
      "value_display": "Choppy",
      "score": 50,
      "ai_analysis": "MACD momentum is weakening, potential pullback ahead.  RSI (46.3) is in neutral zone.  Price broke below Bollinger Lower Band. Mean reversion expected.",
      "sparkline": [
        310.260009765625,
        311.2300109863281,
        307.3399963378906,
        307.3399963378906,
        307.3399963378906,
        301.5400085449219,
        301.5400085449219
      ],
      "stats": {
        "rsi": "46.3",
        "vol_ratio": "1.4x",
        "high_24h": "317.40",
        "low_24h": "301.17"
      }
    },
    {
      "id": "MSFT_1780984680",
      "symbol": "MSFT",
      "asset_type": "Stock",
      "price": "411.74",
      "signal_type": "Watching",
      "action": "Watch",
      "value_display": "Choppy",
      "score": 50,
      "ai_analysis": "MACD momentum is weakening, potential pullback ahead.  RSI (41.4) is in neutral zone.",
      "sparkline": [
        427.3399963378906,
        428.04998779296875,
        416.6700134277344,
        416.6700134277344,
        416.6700134277344,
        411.739990234375,
        411.739990234375
      ],
      "stats": {
        "rsi": "41.4",
        "vol_ratio": "0.8x",
        "high_24h": "417.16",
        "low_24h": "408.56"
      }
    },
    {
      "id": "COIN_1780984680",
      "symbol": "COIN",
      "asset_type": "Stock",
      "price": "162.11",
      "signal_type": "Watching",
      "action": "Watch",
      "value_display": "Choppy",
      "score": 50,
      "ai_analysis": "MACD momentum is weakening, potential pullback ahead.  RSI (38.0) is in neutral zone.",
      "sparkline": [
        163.22000122070312,
        164.1300048828125,
        152.39999389648438,
        152.39999389648438,
        152.39999389648438,
        162.11000061035156,
        162.11000061035156
      ],
      "stats": {
        "rsi": "38.0",
        "vol_ratio": "0.9x",
        "high_24h": "164.28",
        "low_24h": "154.98"
      }
    },
    {
      "id": "MSTR_1780984680",
      "symbol": "MSTR",
      "asset_type": "Stock",
      "price": "127.20",
      "signal_type": "Watching",
      "action": "Watch",
      "value_display": "Choppy",
      "score": 50,
      "ai_analysis": "MACD momentum is weakening, potential pullback ahead.  RSI (31.5) is in neutral zone.",
      "sparkline": [
        126.55000305175781,
        129.3699951171875,
        120.44000244140625,
        120.44000244140625,
        120.44000244140625,
        127.19999694824219,
        127.19999694824219
      ],
      "stats": {
        "rsi": "31.5",
        "vol_ratio": "1.0x",
        "high_24h": "129.00",
        "low_24h": "123.15"
      }
    }
  ]
}